{
  "@context": [
    "http://www.w3.org/ns/anno.jsonld",
    "http://iiif.io/api/presentation/3/context.json"
  ],
  "id": "https://toho-digital-library.zinbun.kyoto-u.ac.jp/manifests/M043.json",
  "type": "Manifest",
  "label": {
    "zh": [
      "大乘華嚴經略策　一卷　入法界十八問答　一卷　華嚴講主自問自答　一卷"
    ],
    "en": [
      "大乘華嚴經略策　一卷　入法界十八問答　一卷　華嚴講主自問自答　一卷"
    ]
  },
  "metadata": [
    {
      "label": {
        "en": [
          "Title"
        ],
        "zh": [
          "書名"
        ]
      },
      "value": {
        "zh": [
          "大乘華嚴經略策　一卷　入法界十八問答　一卷　華嚴講主自問自答　一卷"
        ]
      }
    },
    {
      "label": {
        "en": [
          "Category"
        ],
        "zh": [
          "類別"
        ]
      },
      "value": {
        "zh": [
          "松本文庫"
        ]
      }
    },
    {
      "label": {
        "en": [
          "Author(s)"
        ],
        "zh": [
          "作者"
        ]
      },
      "value": {
        "zh": [
          "唐釋澄觀"
        ]
      }
    },
    {
      "label": {
        "en": [
          "Dynasty"
        ],
        "zh": [
          "朝代"
        ]
      },
      "value": {
        "zh": [
          "唐"
        ]
      }
    },
    {
      "label": {
        "en": [
          "Publication Info"
        ],
        "zh": [
          "版本信息"
        ]
      },
      "value": {
        "zh": [
          "唐釋澄觀撰　鈔本"
        ]
      }
    },
    {
      "label": {
        "en": [
          "Volumes"
        ],
        "zh": [
          "卷數"
        ]
      },
      "value": {
        "zh": [
          "一卷"
        ]
      }
    },
    {
      "label": {
        "en": [
          "Book Type"
        ],
        "zh": [
          "版本類型"
        ]
      },
      "value": {
        "zh": [
          "手鈔本"
        ]
      }
    }
  ],
  "summary": {
    "zh": [
      "唐釋澄觀撰　鈔本"
    ],
    "en": [
      "唐釋澄觀撰　鈔本"
    ]
  },
  "viewingDirection": "right-to-left",
  "requiredStatement": {
    "label": {
      "en": [
        "Attribution"
      ],
      "zh": [
        "歸屬"
      ]
    },
    "value": {
      "zh": [
        "東方學数字圖書館"
      ],
      "ja": [
        "東方學デジタル圖書館"
      ],
      "en": [
        "Oriental Studies Digital Library"
      ]
    }
  },
  "rights": "http://creativecommons.org/licenses/by-nc/4.0/",
  "provider": [
    {
      "id": "https://toho-digital-library.zinbun.kyoto-u.ac.jp",
      "type": "Agent",
      "label": {
        "ja": [
          "東方學デジタル圖書館"
        ]
      },
      "homepage": [
        {
          "id": "https://toho-digital-library.zinbun.kyoto-u.ac.jp",
          "type": "Text",
          "label": {
            "ja": [
              "東方學デジタル圖書館"
            ]
          },
          "format": "text/html"
        }
      ]
    }
  ],
  "items": [
    {
      "id": "https://toho-digital-library.zinbun.kyoto-u.ac.jp/canvas/M043/M0430001_1",
      "type": "Canvas",
      "label": {
        "zh": [
          "裏 - 第1頁"
        ],
        "en": [
          "裏 - 第1頁"
        ]
      },
      "height": 1400,
      "width": 1000,
      "items": [
        {
          "id": "https://toho-digital-library.zinbun.kyoto-u.ac.jp/canvas/M043/M0430001_1/page/1",
          "type": "AnnotationPage",
          "items": [
            {
              "id": "https://toho-digital-library.zinbun.kyoto-u.ac.jp/canvas/M043/M0430001_1/annotation/1",
              "type": "Annotation",
              "motivation": "painting",
              "body": {
                "id": "https://iiif.toyjack.net/iiif/M043/M0430001_001.jpg",
                "type": "Image",
                "format": "image/jpeg",
                "height": 1400,
                "width": 1000,
                "service": [
                  {
                    "@id": "https://iiif.toyjack.net/iiif/M043%2FM0430001",
                    "@type": "ImageService2",
                    "profile": "http://iiif.io/api/image/2/level2.json"
                  }
                ]
              },
              "target": "https://toho-digital-library.zinbun.kyoto-u.ac.jp/canvas/M043/M0430001_1"
            }
          ]
        }
      ]
    },
    {
      "id": "https://toho-digital-library.zinbun.kyoto-u.ac.jp/canvas/M043/M0430001_2",
      "type": "Canvas",
      "label": {
        "zh": [
          "裏 - 第2頁"
        ],
        "en": [
          "裏 - 第2頁"
        ]
      },
      "height": 1400,
      "width": 1000,
      "items": [
        {
          "id": "https://toho-digital-library.zinbun.kyoto-u.ac.jp/canvas/M043/M0430001_2/page/1",
          "type": "AnnotationPage",
          "items": [
            {
              "id": "https://toho-digital-library.zinbun.kyoto-u.ac.jp/canvas/M043/M0430001_2/annotation/1",
              "type": "Annotation",
              "motivation": "painting",
              "body": {
                "id": "https://iiif.toyjack.net/iiif/M043/M0430001_002.jpg",
                "type": "Image",
                "format": "image/jpeg",
                "height": 1400,
                "width": 1000,
                "service": [
                  {
                    "@id": "https://iiif.toyjack.net/iiif/M043%2FM0430002",
                    "@type": "ImageService2",
                    "profile": "http://iiif.io/api/image/2/level2.json"
                  }
                ]
              },
              "target": "https://toho-digital-library.zinbun.kyoto-u.ac.jp/canvas/M043/M0430001_2"
            }
          ]
        }
      ]
    },
    {
      "id": "https://toho-digital-library.zinbun.kyoto-u.ac.jp/canvas/M043/M0430001_3",
      "type": "Canvas",
      "label": {
        "zh": [
          "裏 - 第3頁"
        ],
        "en": [
          "裏 - 第3頁"
        ]
      },
      "height": 1400,
      "width": 1000,
      "items": [
        {
          "id": "https://toho-digital-library.zinbun.kyoto-u.ac.jp/canvas/M043/M0430001_3/page/1",
          "type": "AnnotationPage",
          "items": [
            {
              "id": "https://toho-digital-library.zinbun.kyoto-u.ac.jp/canvas/M043/M0430001_3/annotation/1",
              "type": "Annotation",
              "motivation": "painting",
              "body": {
                "id": "https://iiif.toyjack.net/iiif/M043/M0430001_003.jpg",
                "type": "Image",
                "format": "image/jpeg",
                "height": 1400,
                "width": 1000,
                "service": [
                  {
                    "@id": "https://iiif.toyjack.net/iiif/M043%2FM0430003",
                    "@type": "ImageService2",
                    "profile": "http://iiif.io/api/image/2/level2.json"
                  }
                ]
              },
              "target": "https://toho-digital-library.zinbun.kyoto-u.ac.jp/canvas/M043/M0430001_3"
            }
          ]
        }
      ]
    },
    {
      "id": "https://toho-digital-library.zinbun.kyoto-u.ac.jp/canvas/M043/M0430001_4",
      "type": "Canvas",
      "label": {
        "zh": [
          "裏 - 第4頁"
        ],
        "en": [
          "裏 - 第4頁"
        ]
      },
      "height": 1400,
      "width": 1000,
      "items": [
        {
          "id": "https://toho-digital-library.zinbun.kyoto-u.ac.jp/canvas/M043/M0430001_4/page/1",
          "type": "AnnotationPage",
          "items": [
            {
              "id": "https://toho-digital-library.zinbun.kyoto-u.ac.jp/canvas/M043/M0430001_4/annotation/1",
              "type": "Annotation",
              "motivation": "painting",
              "body": {
                "id": "https://iiif.toyjack.net/iiif/M043/M0430001_004.jpg",
                "type": "Image",
                "format": "image/jpeg",
                "height": 1400,
                "width": 1000,
                "service": [
                  {
                    "@id": "https://iiif.toyjack.net/iiif/M043%2FM0430004",
                    "@type": "ImageService2",
                    "profile": "http://iiif.io/api/image/2/level2.json"
                  }
                ]
              },
              "target": "https://toho-digital-library.zinbun.kyoto-u.ac.jp/canvas/M043/M0430001_4"
            }
          ]
        }
      ]
    },
    {
      "id": "https://toho-digital-library.zinbun.kyoto-u.ac.jp/canvas/M043/M0430001_5",
      "type": "Canvas",
      "label": {
        "zh": [
          "裏 - 第5頁"
        ],
        "en": [
          "裏 - 第5頁"
        ]
      },
      "height": 1400,
      "width": 1000,
      "items": [
        {
          "id": "https://toho-digital-library.zinbun.kyoto-u.ac.jp/canvas/M043/M0430001_5/page/1",
          "type": "AnnotationPage",
          "items": [
            {
              "id": "https://toho-digital-library.zinbun.kyoto-u.ac.jp/canvas/M043/M0430001_5/annotation/1",
              "type": "Annotation",
              "motivation": "painting",
              "body": {
                "id": "https://iiif.toyjack.net/iiif/M043/M0430001_005.jpg",
                "type": "Image",
                "format": "image/jpeg",
                "height": 1400,
                "width": 1000,
                "service": [
                  {
                    "@id": "https://iiif.toyjack.net/iiif/M043%2FM0430005",
                    "@type": "ImageService2",
                    "profile": "http://iiif.io/api/image/2/level2.json"
                  }
                ]
              },
              "target": "https://toho-digital-library.zinbun.kyoto-u.ac.jp/canvas/M043/M0430001_5"
            }
          ]
        }
      ]
    },
    {
      "id": "https://toho-digital-library.zinbun.kyoto-u.ac.jp/canvas/M043/M0430001_6",
      "type": "Canvas",
      "label": {
        "zh": [
          "裏 - 第6頁"
        ],
        "en": [
          "裏 - 第6頁"
        ]
      },
      "height": 1400,
      "width": 1000,
      "items": [
        {
          "id": "https://toho-digital-library.zinbun.kyoto-u.ac.jp/canvas/M043/M0430001_6/page/1",
          "type": "AnnotationPage",
          "items": [
            {
              "id": "https://toho-digital-library.zinbun.kyoto-u.ac.jp/canvas/M043/M0430001_6/annotation/1",
              "type": "Annotation",
              "motivation": "painting",
              "body": {
                "id": "https://iiif.toyjack.net/iiif/M043/M0430001_006.jpg",
                "type": "Image",
                "format": "image/jpeg",
                "height": 1400,
                "width": 1000,
                "service": [
                  {
                    "@id": "https://iiif.toyjack.net/iiif/M043%2FM0430006",
                    "@type": "ImageService2",
                    "profile": "http://iiif.io/api/image/2/level2.json"
                  }
                ]
              },
              "target": "https://toho-digital-library.zinbun.kyoto-u.ac.jp/canvas/M043/M0430001_6"
            }
          ]
        }
      ]
    },
    {
      "id": "https://toho-digital-library.zinbun.kyoto-u.ac.jp/canvas/M043/M0430001_7",
      "type": "Canvas",
      "label": {
        "zh": [
          "裏 - 第7頁"
        ],
        "en": [
          "裏 - 第7頁"
        ]
      },
      "height": 1400,
      "width": 1000,
      "items": [
        {
          "id": "https://toho-digital-library.zinbun.kyoto-u.ac.jp/canvas/M043/M0430001_7/page/1",
          "type": "AnnotationPage",
          "items": [
            {
              "id": "https://toho-digital-library.zinbun.kyoto-u.ac.jp/canvas/M043/M0430001_7/annotation/1",
              "type": "Annotation",
              "motivation": "painting",
              "body": {
                "id": "https://iiif.toyjack.net/iiif/M043/M0430001_007.jpg",
                "type": "Image",
                "format": "image/jpeg",
                "height": 1400,
                "width": 1000,
                "service": [
                  {
                    "@id": "https://iiif.toyjack.net/iiif/M043%2FM0430007",
                    "@type": "ImageService2",
                    "profile": "http://iiif.io/api/image/2/level2.json"
                  }
                ]
              },
              "target": "https://toho-digital-library.zinbun.kyoto-u.ac.jp/canvas/M043/M0430001_7"
            }
          ]
        }
      ]
    },
    {
      "id": "https://toho-digital-library.zinbun.kyoto-u.ac.jp/canvas/M043/M0430001_8",
      "type": "Canvas",
      "label": {
        "zh": [
          "裏 - 第8頁"
        ],
        "en": [
          "裏 - 第8頁"
        ]
      },
      "height": 1400,
      "width": 1000,
      "items": [
        {
          "id": "https://toho-digital-library.zinbun.kyoto-u.ac.jp/canvas/M043/M0430001_8/page/1",
          "type": "AnnotationPage",
          "items": [
            {
              "id": "https://toho-digital-library.zinbun.kyoto-u.ac.jp/canvas/M043/M0430001_8/annotation/1",
              "type": "Annotation",
              "motivation": "painting",
              "body": {
                "id": "https://iiif.toyjack.net/iiif/M043/M0430001_008.jpg",
                "type": "Image",
                "format": "image/jpeg",
                "height": 1400,
                "width": 1000,
                "service": [
                  {
                    "@id": "https://iiif.toyjack.net/iiif/M043%2FM0430008",
                    "@type": "ImageService2",
                    "profile": "http://iiif.io/api/image/2/level2.json"
                  }
                ]
              },
              "target": "https://toho-digital-library.zinbun.kyoto-u.ac.jp/canvas/M043/M0430001_8"
            }
          ]
        }
      ]
    },
    {
      "id": "https://toho-digital-library.zinbun.kyoto-u.ac.jp/canvas/M043/M0430001_9",
      "type": "Canvas",
      "label": {
        "zh": [
          "裏 - 第9頁"
        ],
        "en": [
          "裏 - 第9頁"
        ]
      },
      "height": 1400,
      "width": 1000,
      "items": [
        {
          "id": "https://toho-digital-library.zinbun.kyoto-u.ac.jp/canvas/M043/M0430001_9/page/1",
          "type": "AnnotationPage",
          "items": [
            {
              "id": "https://toho-digital-library.zinbun.kyoto-u.ac.jp/canvas/M043/M0430001_9/annotation/1",
              "type": "Annotation",
              "motivation": "painting",
              "body": {
                "id": "https://iiif.toyjack.net/iiif/M043/M0430001_009.jpg",
                "type": "Image",
                "format": "image/jpeg",
                "height": 1400,
                "width": 1000,
                "service": [
                  {
                    "@id": "https://iiif.toyjack.net/iiif/M043%2FM0430009",
                    "@type": "ImageService2",
                    "profile": "http://iiif.io/api/image/2/level2.json"
                  }
                ]
              },
              "target": "https://toho-digital-library.zinbun.kyoto-u.ac.jp/canvas/M043/M0430001_9"
            }
          ]
        }
      ]
    },
    {
      "id": "https://toho-digital-library.zinbun.kyoto-u.ac.jp/canvas/M043/M0430001_10",
      "type": "Canvas",
      "label": {
        "zh": [
          "裏 - 第10頁"
        ],
        "en": [
          "裏 - 第10頁"
        ]
      },
      "height": 1400,
      "width": 1000,
      "items": [
        {
          "id": "https://toho-digital-library.zinbun.kyoto-u.ac.jp/canvas/M043/M0430001_10/page/1",
          "type": "AnnotationPage",
          "items": [
            {
              "id": "https://toho-digital-library.zinbun.kyoto-u.ac.jp/canvas/M043/M0430001_10/annotation/1",
              "type": "Annotation",
              "motivation": "painting",
              "body": {
                "id": "https://iiif.toyjack.net/iiif/M043/M0430001_010.jpg",
                "type": "Image",
                "format": "image/jpeg",
                "height": 1400,
                "width": 1000,
                "service": [
                  {
                    "@id": "https://iiif.toyjack.net/iiif/M043%2FM0430010",
                    "@type": "ImageService2",
                    "profile": "http://iiif.io/api/image/2/level2.json"
                  }
                ]
              },
              "target": "https://toho-digital-library.zinbun.kyoto-u.ac.jp/canvas/M043/M0430001_10"
            }
          ]
        }
      ]
    },
    {
      "id": "https://toho-digital-library.zinbun.kyoto-u.ac.jp/canvas/M043/M0430001_11",
      "type": "Canvas",
      "label": {
        "zh": [
          "裏 - 第11頁"
        ],
        "en": [
          "裏 - 第11頁"
        ]
      },
      "height": 1400,
      "width": 1000,
      "items": [
        {
          "id": "https://toho-digital-library.zinbun.kyoto-u.ac.jp/canvas/M043/M0430001_11/page/1",
          "type": "AnnotationPage",
          "items": [
            {
              "id": "https://toho-digital-library.zinbun.kyoto-u.ac.jp/canvas/M043/M0430001_11/annotation/1",
              "type": "Annotation",
              "motivation": "painting",
              "body": {
                "id": "https://iiif.toyjack.net/iiif/M043/M0430001_011.jpg",
                "type": "Image",
                "format": "image/jpeg",
                "height": 1400,
                "width": 1000,
                "service": [
                  {
                    "@id": "https://iiif.toyjack.net/iiif/M043%2FM0430011",
                    "@type": "ImageService2",
                    "profile": "http://iiif.io/api/image/2/level2.json"
                  }
                ]
              },
              "target": "https://toho-digital-library.zinbun.kyoto-u.ac.jp/canvas/M043/M0430001_11"
            }
          ]
        }
      ]
    },
    {
      "id": "https://toho-digital-library.zinbun.kyoto-u.ac.jp/canvas/M043/M0430001_12",
      "type": "Canvas",
      "label": {
        "zh": [
          "裏 - 第12頁"
        ],
        "en": [
          "裏 - 第12頁"
        ]
      },
      "height": 1400,
      "width": 1000,
      "items": [
        {
          "id": "https://toho-digital-library.zinbun.kyoto-u.ac.jp/canvas/M043/M0430001_12/page/1",
          "type": "AnnotationPage",
          "items": [
            {
              "id": "https://toho-digital-library.zinbun.kyoto-u.ac.jp/canvas/M043/M0430001_12/annotation/1",
              "type": "Annotation",
              "motivation": "painting",
              "body": {
                "id": "https://iiif.toyjack.net/iiif/M043/M0430001_012.jpg",
                "type": "Image",
                "format": "image/jpeg",
                "height": 1400,
                "width": 1000,
                "service": [
                  {
                    "@id": "https://iiif.toyjack.net/iiif/M043%2FM0430012",
                    "@type": "ImageService2",
                    "profile": "http://iiif.io/api/image/2/level2.json"
                  }
                ]
              },
              "target": "https://toho-digital-library.zinbun.kyoto-u.ac.jp/canvas/M043/M0430001_12"
            }
          ]
        }
      ]
    },
    {
      "id": "https://toho-digital-library.zinbun.kyoto-u.ac.jp/canvas/M043/M0430001_13",
      "type": "Canvas",
      "label": {
        "zh": [
          "裏 - 第13頁"
        ],
        "en": [
          "裏 - 第13頁"
        ]
      },
      "height": 1400,
      "width": 1000,
      "items": [
        {
          "id": "https://toho-digital-library.zinbun.kyoto-u.ac.jp/canvas/M043/M0430001_13/page/1",
          "type": "AnnotationPage",
          "items": [
            {
              "id": "https://toho-digital-library.zinbun.kyoto-u.ac.jp/canvas/M043/M0430001_13/annotation/1",
              "type": "Annotation",
              "motivation": "painting",
              "body": {
                "id": "https://iiif.toyjack.net/iiif/M043/M0430001_013.jpg",
                "type": "Image",
                "format": "image/jpeg",
                "height": 1400,
                "width": 1000,
                "service": [
                  {
                    "@id": "https://iiif.toyjack.net/iiif/M043%2FM0430013",
                    "@type": "ImageService2",
                    "profile": "http://iiif.io/api/image/2/level2.json"
                  }
                ]
              },
              "target": "https://toho-digital-library.zinbun.kyoto-u.ac.jp/canvas/M043/M0430001_13"
            }
          ]
        }
      ]
    },
    {
      "id": "https://toho-digital-library.zinbun.kyoto-u.ac.jp/canvas/M043/M0430001_14",
      "type": "Canvas",
      "label": {
        "zh": [
          "裏 - 第14頁"
        ],
        "en": [
          "裏 - 第14頁"
        ]
      },
      "height": 1400,
      "width": 1000,
      "items": [
        {
          "id": "https://toho-digital-library.zinbun.kyoto-u.ac.jp/canvas/M043/M0430001_14/page/1",
          "type": "AnnotationPage",
          "items": [
            {
              "id": "https://toho-digital-library.zinbun.kyoto-u.ac.jp/canvas/M043/M0430001_14/annotation/1",
              "type": "Annotation",
              "motivation": "painting",
              "body": {
                "id": "https://iiif.toyjack.net/iiif/M043/M0430001_014.jpg",
                "type": "Image",
                "format": "image/jpeg",
                "height": 1400,
                "width": 1000,
                "service": [
                  {
                    "@id": "https://iiif.toyjack.net/iiif/M043%2FM0430014",
                    "@type": "ImageService2",
                    "profile": "http://iiif.io/api/image/2/level2.json"
                  }
                ]
              },
              "target": "https://toho-digital-library.zinbun.kyoto-u.ac.jp/canvas/M043/M0430001_14"
            }
          ]
        }
      ]
    },
    {
      "id": "https://toho-digital-library.zinbun.kyoto-u.ac.jp/canvas/M043/M0430001_15",
      "type": "Canvas",
      "label": {
        "zh": [
          "裏 - 第15頁"
        ],
        "en": [
          "裏 - 第15頁"
        ]
      },
      "height": 1400,
      "width": 1000,
      "items": [
        {
          "id": "https://toho-digital-library.zinbun.kyoto-u.ac.jp/canvas/M043/M0430001_15/page/1",
          "type": "AnnotationPage",
          "items": [
            {
              "id": "https://toho-digital-library.zinbun.kyoto-u.ac.jp/canvas/M043/M0430001_15/annotation/1",
              "type": "Annotation",
              "motivation": "painting",
              "body": {
                "id": "https://iiif.toyjack.net/iiif/M043/M0430001_015.jpg",
                "type": "Image",
                "format": "image/jpeg",
                "height": 1400,
                "width": 1000,
                "service": [
                  {
                    "@id": "https://iiif.toyjack.net/iiif/M043%2FM0430015",
                    "@type": "ImageService2",
                    "profile": "http://iiif.io/api/image/2/level2.json"
                  }
                ]
              },
              "target": "https://toho-digital-library.zinbun.kyoto-u.ac.jp/canvas/M043/M0430001_15"
            }
          ]
        }
      ]
    },
    {
      "id": "https://toho-digital-library.zinbun.kyoto-u.ac.jp/canvas/M043/M0430001_16",
      "type": "Canvas",
      "label": {
        "zh": [
          "裏 - 第16頁"
        ],
        "en": [
          "裏 - 第16頁"
        ]
      },
      "height": 1400,
      "width": 1000,
      "items": [
        {
          "id": "https://toho-digital-library.zinbun.kyoto-u.ac.jp/canvas/M043/M0430001_16/page/1",
          "type": "AnnotationPage",
          "items": [
            {
              "id": "https://toho-digital-library.zinbun.kyoto-u.ac.jp/canvas/M043/M0430001_16/annotation/1",
              "type": "Annotation",
              "motivation": "painting",
              "body": {
                "id": "https://iiif.toyjack.net/iiif/M043/M0430001_016.jpg",
                "type": "Image",
                "format": "image/jpeg",
                "height": 1400,
                "width": 1000,
                "service": [
                  {
                    "@id": "https://iiif.toyjack.net/iiif/M043%2FM0430016",
                    "@type": "ImageService2",
                    "profile": "http://iiif.io/api/image/2/level2.json"
                  }
                ]
              },
              "target": "https://toho-digital-library.zinbun.kyoto-u.ac.jp/canvas/M043/M0430001_16"
            }
          ]
        }
      ]
    },
    {
      "id": "https://toho-digital-library.zinbun.kyoto-u.ac.jp/canvas/M043/M0430001_17",
      "type": "Canvas",
      "label": {
        "zh": [
          "裏 - 第17頁"
        ],
        "en": [
          "裏 - 第17頁"
        ]
      },
      "height": 1400,
      "width": 1000,
      "items": [
        {
          "id": "https://toho-digital-library.zinbun.kyoto-u.ac.jp/canvas/M043/M0430001_17/page/1",
          "type": "AnnotationPage",
          "items": [
            {
              "id": "https://toho-digital-library.zinbun.kyoto-u.ac.jp/canvas/M043/M0430001_17/annotation/1",
              "type": "Annotation",
              "motivation": "painting",
              "body": {
                "id": "https://iiif.toyjack.net/iiif/M043/M0430001_017.jpg",
                "type": "Image",
                "format": "image/jpeg",
                "height": 1400,
                "width": 1000,
                "service": [
                  {
                    "@id": "https://iiif.toyjack.net/iiif/M043%2FM0430017",
                    "@type": "ImageService2",
                    "profile": "http://iiif.io/api/image/2/level2.json"
                  }
                ]
              },
              "target": "https://toho-digital-library.zinbun.kyoto-u.ac.jp/canvas/M043/M0430001_17"
            }
          ]
        }
      ]
    },
    {
      "id": "https://toho-digital-library.zinbun.kyoto-u.ac.jp/canvas/M043/M0430001_18",
      "type": "Canvas",
      "label": {
        "zh": [
          "裏 - 第18頁"
        ],
        "en": [
          "裏 - 第18頁"
        ]
      },
      "height": 1400,
      "width": 1000,
      "items": [
        {
          "id": "https://toho-digital-library.zinbun.kyoto-u.ac.jp/canvas/M043/M0430001_18/page/1",
          "type": "AnnotationPage",
          "items": [
            {
              "id": "https://toho-digital-library.zinbun.kyoto-u.ac.jp/canvas/M043/M0430001_18/annotation/1",
              "type": "Annotation",
              "motivation": "painting",
              "body": {
                "id": "https://iiif.toyjack.net/iiif/M043/M0430001_018.jpg",
                "type": "Image",
                "format": "image/jpeg",
                "height": 1400,
                "width": 1000,
                "service": [
                  {
                    "@id": "https://iiif.toyjack.net/iiif/M043%2FM0430018",
                    "@type": "ImageService2",
                    "profile": "http://iiif.io/api/image/2/level2.json"
                  }
                ]
              },
              "target": "https://toho-digital-library.zinbun.kyoto-u.ac.jp/canvas/M043/M0430001_18"
            }
          ]
        }
      ]
    },
    {
      "id": "https://toho-digital-library.zinbun.kyoto-u.ac.jp/canvas/M043/M0430002_1",
      "type": "Canvas",
      "label": {
        "zh": [
          "表 - 第1頁"
        ],
        "en": [
          "表 - 第1頁"
        ]
      },
      "height": 1400,
      "width": 1000,
      "items": [
        {
          "id": "https://toho-digital-library.zinbun.kyoto-u.ac.jp/canvas/M043/M0430002_1/page/1",
          "type": "AnnotationPage",
          "items": [
            {
              "id": "https://toho-digital-library.zinbun.kyoto-u.ac.jp/canvas/M043/M0430002_1/annotation/1",
              "type": "Annotation",
              "motivation": "painting",
              "body": {
                "id": "https://iiif.toyjack.net/iiif/M043/M0430002_001.jpg",
                "type": "Image",
                "format": "image/jpeg",
                "height": 1400,
                "width": 1000,
                "service": [
                  {
                    "@id": "https://iiif.toyjack.net/iiif/M043%2FM0430001",
                    "@type": "ImageService2",
                    "profile": "http://iiif.io/api/image/2/level2.json"
                  }
                ]
              },
              "target": "https://toho-digital-library.zinbun.kyoto-u.ac.jp/canvas/M043/M0430002_1"
            }
          ]
        }
      ]
    },
    {
      "id": "https://toho-digital-library.zinbun.kyoto-u.ac.jp/canvas/M043/M0430002_2",
      "type": "Canvas",
      "label": {
        "zh": [
          "表 - 第2頁"
        ],
        "en": [
          "表 - 第2頁"
        ]
      },
      "height": 1400,
      "width": 1000,
      "items": [
        {
          "id": "https://toho-digital-library.zinbun.kyoto-u.ac.jp/canvas/M043/M0430002_2/page/1",
          "type": "AnnotationPage",
          "items": [
            {
              "id": "https://toho-digital-library.zinbun.kyoto-u.ac.jp/canvas/M043/M0430002_2/annotation/1",
              "type": "Annotation",
              "motivation": "painting",
              "body": {
                "id": "https://iiif.toyjack.net/iiif/M043/M0430002_002.jpg",
                "type": "Image",
                "format": "image/jpeg",
                "height": 1400,
                "width": 1000,
                "service": [
                  {
                    "@id": "https://iiif.toyjack.net/iiif/M043%2FM0430002",
                    "@type": "ImageService2",
                    "profile": "http://iiif.io/api/image/2/level2.json"
                  }
                ]
              },
              "target": "https://toho-digital-library.zinbun.kyoto-u.ac.jp/canvas/M043/M0430002_2"
            }
          ]
        }
      ]
    },
    {
      "id": "https://toho-digital-library.zinbun.kyoto-u.ac.jp/canvas/M043/M0430002_3",
      "type": "Canvas",
      "label": {
        "zh": [
          "表 - 第3頁"
        ],
        "en": [
          "表 - 第3頁"
        ]
      },
      "height": 1400,
      "width": 1000,
      "items": [
        {
          "id": "https://toho-digital-library.zinbun.kyoto-u.ac.jp/canvas/M043/M0430002_3/page/1",
          "type": "AnnotationPage",
          "items": [
            {
              "id": "https://toho-digital-library.zinbun.kyoto-u.ac.jp/canvas/M043/M0430002_3/annotation/1",
              "type": "Annotation",
              "motivation": "painting",
              "body": {
                "id": "https://iiif.toyjack.net/iiif/M043/M0430002_003.jpg",
                "type": "Image",
                "format": "image/jpeg",
                "height": 1400,
                "width": 1000,
                "service": [
                  {
                    "@id": "https://iiif.toyjack.net/iiif/M043%2FM0430003",
                    "@type": "ImageService2",
                    "profile": "http://iiif.io/api/image/2/level2.json"
                  }
                ]
              },
              "target": "https://toho-digital-library.zinbun.kyoto-u.ac.jp/canvas/M043/M0430002_3"
            }
          ]
        }
      ]
    },
    {
      "id": "https://toho-digital-library.zinbun.kyoto-u.ac.jp/canvas/M043/M0430002_4",
      "type": "Canvas",
      "label": {
        "zh": [
          "表 - 第4頁"
        ],
        "en": [
          "表 - 第4頁"
        ]
      },
      "height": 1400,
      "width": 1000,
      "items": [
        {
          "id": "https://toho-digital-library.zinbun.kyoto-u.ac.jp/canvas/M043/M0430002_4/page/1",
          "type": "AnnotationPage",
          "items": [
            {
              "id": "https://toho-digital-library.zinbun.kyoto-u.ac.jp/canvas/M043/M0430002_4/annotation/1",
              "type": "Annotation",
              "motivation": "painting",
              "body": {
                "id": "https://iiif.toyjack.net/iiif/M043/M0430002_004.jpg",
                "type": "Image",
                "format": "image/jpeg",
                "height": 1400,
                "width": 1000,
                "service": [
                  {
                    "@id": "https://iiif.toyjack.net/iiif/M043%2FM0430004",
                    "@type": "ImageService2",
                    "profile": "http://iiif.io/api/image/2/level2.json"
                  }
                ]
              },
              "target": "https://toho-digital-library.zinbun.kyoto-u.ac.jp/canvas/M043/M0430002_4"
            }
          ]
        }
      ]
    },
    {
      "id": "https://toho-digital-library.zinbun.kyoto-u.ac.jp/canvas/M043/M0430002_5",
      "type": "Canvas",
      "label": {
        "zh": [
          "表 - 第5頁"
        ],
        "en": [
          "表 - 第5頁"
        ]
      },
      "height": 1400,
      "width": 1000,
      "items": [
        {
          "id": "https://toho-digital-library.zinbun.kyoto-u.ac.jp/canvas/M043/M0430002_5/page/1",
          "type": "AnnotationPage",
          "items": [
            {
              "id": "https://toho-digital-library.zinbun.kyoto-u.ac.jp/canvas/M043/M0430002_5/annotation/1",
              "type": "Annotation",
              "motivation": "painting",
              "body": {
                "id": "https://iiif.toyjack.net/iiif/M043/M0430002_005.jpg",
                "type": "Image",
                "format": "image/jpeg",
                "height": 1400,
                "width": 1000,
                "service": [
                  {
                    "@id": "https://iiif.toyjack.net/iiif/M043%2FM0430005",
                    "@type": "ImageService2",
                    "profile": "http://iiif.io/api/image/2/level2.json"
                  }
                ]
              },
              "target": "https://toho-digital-library.zinbun.kyoto-u.ac.jp/canvas/M043/M0430002_5"
            }
          ]
        }
      ]
    },
    {
      "id": "https://toho-digital-library.zinbun.kyoto-u.ac.jp/canvas/M043/M0430002_6",
      "type": "Canvas",
      "label": {
        "zh": [
          "表 - 第6頁"
        ],
        "en": [
          "表 - 第6頁"
        ]
      },
      "height": 1400,
      "width": 1000,
      "items": [
        {
          "id": "https://toho-digital-library.zinbun.kyoto-u.ac.jp/canvas/M043/M0430002_6/page/1",
          "type": "AnnotationPage",
          "items": [
            {
              "id": "https://toho-digital-library.zinbun.kyoto-u.ac.jp/canvas/M043/M0430002_6/annotation/1",
              "type": "Annotation",
              "motivation": "painting",
              "body": {
                "id": "https://iiif.toyjack.net/iiif/M043/M0430002_006.jpg",
                "type": "Image",
                "format": "image/jpeg",
                "height": 1400,
                "width": 1000,
                "service": [
                  {
                    "@id": "https://iiif.toyjack.net/iiif/M043%2FM0430006",
                    "@type": "ImageService2",
                    "profile": "http://iiif.io/api/image/2/level2.json"
                  }
                ]
              },
              "target": "https://toho-digital-library.zinbun.kyoto-u.ac.jp/canvas/M043/M0430002_6"
            }
          ]
        }
      ]
    },
    {
      "id": "https://toho-digital-library.zinbun.kyoto-u.ac.jp/canvas/M043/M0430002_7",
      "type": "Canvas",
      "label": {
        "zh": [
          "表 - 第7頁"
        ],
        "en": [
          "表 - 第7頁"
        ]
      },
      "height": 1400,
      "width": 1000,
      "items": [
        {
          "id": "https://toho-digital-library.zinbun.kyoto-u.ac.jp/canvas/M043/M0430002_7/page/1",
          "type": "AnnotationPage",
          "items": [
            {
              "id": "https://toho-digital-library.zinbun.kyoto-u.ac.jp/canvas/M043/M0430002_7/annotation/1",
              "type": "Annotation",
              "motivation": "painting",
              "body": {
                "id": "https://iiif.toyjack.net/iiif/M043/M0430002_007.jpg",
                "type": "Image",
                "format": "image/jpeg",
                "height": 1400,
                "width": 1000,
                "service": [
                  {
                    "@id": "https://iiif.toyjack.net/iiif/M043%2FM0430007",
                    "@type": "ImageService2",
                    "profile": "http://iiif.io/api/image/2/level2.json"
                  }
                ]
              },
              "target": "https://toho-digital-library.zinbun.kyoto-u.ac.jp/canvas/M043/M0430002_7"
            }
          ]
        }
      ]
    },
    {
      "id": "https://toho-digital-library.zinbun.kyoto-u.ac.jp/canvas/M043/M0430002_8",
      "type": "Canvas",
      "label": {
        "zh": [
          "表 - 第8頁"
        ],
        "en": [
          "表 - 第8頁"
        ]
      },
      "height": 1400,
      "width": 1000,
      "items": [
        {
          "id": "https://toho-digital-library.zinbun.kyoto-u.ac.jp/canvas/M043/M0430002_8/page/1",
          "type": "AnnotationPage",
          "items": [
            {
              "id": "https://toho-digital-library.zinbun.kyoto-u.ac.jp/canvas/M043/M0430002_8/annotation/1",
              "type": "Annotation",
              "motivation": "painting",
              "body": {
                "id": "https://iiif.toyjack.net/iiif/M043/M0430002_008.jpg",
                "type": "Image",
                "format": "image/jpeg",
                "height": 1400,
                "width": 1000,
                "service": [
                  {
                    "@id": "https://iiif.toyjack.net/iiif/M043%2FM0430008",
                    "@type": "ImageService2",
                    "profile": "http://iiif.io/api/image/2/level2.json"
                  }
                ]
              },
              "target": "https://toho-digital-library.zinbun.kyoto-u.ac.jp/canvas/M043/M0430002_8"
            }
          ]
        }
      ]
    },
    {
      "id": "https://toho-digital-library.zinbun.kyoto-u.ac.jp/canvas/M043/M0430002_9",
      "type": "Canvas",
      "label": {
        "zh": [
          "表 - 第9頁"
        ],
        "en": [
          "表 - 第9頁"
        ]
      },
      "height": 1400,
      "width": 1000,
      "items": [
        {
          "id": "https://toho-digital-library.zinbun.kyoto-u.ac.jp/canvas/M043/M0430002_9/page/1",
          "type": "AnnotationPage",
          "items": [
            {
              "id": "https://toho-digital-library.zinbun.kyoto-u.ac.jp/canvas/M043/M0430002_9/annotation/1",
              "type": "Annotation",
              "motivation": "painting",
              "body": {
                "id": "https://iiif.toyjack.net/iiif/M043/M0430002_009.jpg",
                "type": "Image",
                "format": "image/jpeg",
                "height": 1400,
                "width": 1000,
                "service": [
                  {
                    "@id": "https://iiif.toyjack.net/iiif/M043%2FM0430009",
                    "@type": "ImageService2",
                    "profile": "http://iiif.io/api/image/2/level2.json"
                  }
                ]
              },
              "target": "https://toho-digital-library.zinbun.kyoto-u.ac.jp/canvas/M043/M0430002_9"
            }
          ]
        }
      ]
    },
    {
      "id": "https://toho-digital-library.zinbun.kyoto-u.ac.jp/canvas/M043/M0430002_10",
      "type": "Canvas",
      "label": {
        "zh": [
          "表 - 第10頁"
        ],
        "en": [
          "表 - 第10頁"
        ]
      },
      "height": 1400,
      "width": 1000,
      "items": [
        {
          "id": "https://toho-digital-library.zinbun.kyoto-u.ac.jp/canvas/M043/M0430002_10/page/1",
          "type": "AnnotationPage",
          "items": [
            {
              "id": "https://toho-digital-library.zinbun.kyoto-u.ac.jp/canvas/M043/M0430002_10/annotation/1",
              "type": "Annotation",
              "motivation": "painting",
              "body": {
                "id": "https://iiif.toyjack.net/iiif/M043/M0430002_010.jpg",
                "type": "Image",
                "format": "image/jpeg",
                "height": 1400,
                "width": 1000,
                "service": [
                  {
                    "@id": "https://iiif.toyjack.net/iiif/M043%2FM0430010",
                    "@type": "ImageService2",
                    "profile": "http://iiif.io/api/image/2/level2.json"
                  }
                ]
              },
              "target": "https://toho-digital-library.zinbun.kyoto-u.ac.jp/canvas/M043/M0430002_10"
            }
          ]
        }
      ]
    },
    {
      "id": "https://toho-digital-library.zinbun.kyoto-u.ac.jp/canvas/M043/M0430002_11",
      "type": "Canvas",
      "label": {
        "zh": [
          "表 - 第11頁"
        ],
        "en": [
          "表 - 第11頁"
        ]
      },
      "height": 1400,
      "width": 1000,
      "items": [
        {
          "id": "https://toho-digital-library.zinbun.kyoto-u.ac.jp/canvas/M043/M0430002_11/page/1",
          "type": "AnnotationPage",
          "items": [
            {
              "id": "https://toho-digital-library.zinbun.kyoto-u.ac.jp/canvas/M043/M0430002_11/annotation/1",
              "type": "Annotation",
              "motivation": "painting",
              "body": {
                "id": "https://iiif.toyjack.net/iiif/M043/M0430002_011.jpg",
                "type": "Image",
                "format": "image/jpeg",
                "height": 1400,
                "width": 1000,
                "service": [
                  {
                    "@id": "https://iiif.toyjack.net/iiif/M043%2FM0430011",
                    "@type": "ImageService2",
                    "profile": "http://iiif.io/api/image/2/level2.json"
                  }
                ]
              },
              "target": "https://toho-digital-library.zinbun.kyoto-u.ac.jp/canvas/M043/M0430002_11"
            }
          ]
        }
      ]
    },
    {
      "id": "https://toho-digital-library.zinbun.kyoto-u.ac.jp/canvas/M043/M0430002_12",
      "type": "Canvas",
      "label": {
        "zh": [
          "表 - 第12頁"
        ],
        "en": [
          "表 - 第12頁"
        ]
      },
      "height": 1400,
      "width": 1000,
      "items": [
        {
          "id": "https://toho-digital-library.zinbun.kyoto-u.ac.jp/canvas/M043/M0430002_12/page/1",
          "type": "AnnotationPage",
          "items": [
            {
              "id": "https://toho-digital-library.zinbun.kyoto-u.ac.jp/canvas/M043/M0430002_12/annotation/1",
              "type": "Annotation",
              "motivation": "painting",
              "body": {
                "id": "https://iiif.toyjack.net/iiif/M043/M0430002_012.jpg",
                "type": "Image",
                "format": "image/jpeg",
                "height": 1400,
                "width": 1000,
                "service": [
                  {
                    "@id": "https://iiif.toyjack.net/iiif/M043%2FM0430012",
                    "@type": "ImageService2",
                    "profile": "http://iiif.io/api/image/2/level2.json"
                  }
                ]
              },
              "target": "https://toho-digital-library.zinbun.kyoto-u.ac.jp/canvas/M043/M0430002_12"
            }
          ]
        }
      ]
    },
    {
      "id": "https://toho-digital-library.zinbun.kyoto-u.ac.jp/canvas/M043/M0430002_13",
      "type": "Canvas",
      "label": {
        "zh": [
          "表 - 第13頁"
        ],
        "en": [
          "表 - 第13頁"
        ]
      },
      "height": 1400,
      "width": 1000,
      "items": [
        {
          "id": "https://toho-digital-library.zinbun.kyoto-u.ac.jp/canvas/M043/M0430002_13/page/1",
          "type": "AnnotationPage",
          "items": [
            {
              "id": "https://toho-digital-library.zinbun.kyoto-u.ac.jp/canvas/M043/M0430002_13/annotation/1",
              "type": "Annotation",
              "motivation": "painting",
              "body": {
                "id": "https://iiif.toyjack.net/iiif/M043/M0430002_013.jpg",
                "type": "Image",
                "format": "image/jpeg",
                "height": 1400,
                "width": 1000,
                "service": [
                  {
                    "@id": "https://iiif.toyjack.net/iiif/M043%2FM0430013",
                    "@type": "ImageService2",
                    "profile": "http://iiif.io/api/image/2/level2.json"
                  }
                ]
              },
              "target": "https://toho-digital-library.zinbun.kyoto-u.ac.jp/canvas/M043/M0430002_13"
            }
          ]
        }
      ]
    },
    {
      "id": "https://toho-digital-library.zinbun.kyoto-u.ac.jp/canvas/M043/M0430002_14",
      "type": "Canvas",
      "label": {
        "zh": [
          "表 - 第14頁"
        ],
        "en": [
          "表 - 第14頁"
        ]
      },
      "height": 1400,
      "width": 1000,
      "items": [
        {
          "id": "https://toho-digital-library.zinbun.kyoto-u.ac.jp/canvas/M043/M0430002_14/page/1",
          "type": "AnnotationPage",
          "items": [
            {
              "id": "https://toho-digital-library.zinbun.kyoto-u.ac.jp/canvas/M043/M0430002_14/annotation/1",
              "type": "Annotation",
              "motivation": "painting",
              "body": {
                "id": "https://iiif.toyjack.net/iiif/M043/M0430002_014.jpg",
                "type": "Image",
                "format": "image/jpeg",
                "height": 1400,
                "width": 1000,
                "service": [
                  {
                    "@id": "https://iiif.toyjack.net/iiif/M043%2FM0430014",
                    "@type": "ImageService2",
                    "profile": "http://iiif.io/api/image/2/level2.json"
                  }
                ]
              },
              "target": "https://toho-digital-library.zinbun.kyoto-u.ac.jp/canvas/M043/M0430002_14"
            }
          ]
        }
      ]
    },
    {
      "id": "https://toho-digital-library.zinbun.kyoto-u.ac.jp/canvas/M043/M0430002_15",
      "type": "Canvas",
      "label": {
        "zh": [
          "表 - 第15頁"
        ],
        "en": [
          "表 - 第15頁"
        ]
      },
      "height": 1400,
      "width": 1000,
      "items": [
        {
          "id": "https://toho-digital-library.zinbun.kyoto-u.ac.jp/canvas/M043/M0430002_15/page/1",
          "type": "AnnotationPage",
          "items": [
            {
              "id": "https://toho-digital-library.zinbun.kyoto-u.ac.jp/canvas/M043/M0430002_15/annotation/1",
              "type": "Annotation",
              "motivation": "painting",
              "body": {
                "id": "https://iiif.toyjack.net/iiif/M043/M0430002_015.jpg",
                "type": "Image",
                "format": "image/jpeg",
                "height": 1400,
                "width": 1000,
                "service": [
                  {
                    "@id": "https://iiif.toyjack.net/iiif/M043%2FM0430015",
                    "@type": "ImageService2",
                    "profile": "http://iiif.io/api/image/2/level2.json"
                  }
                ]
              },
              "target": "https://toho-digital-library.zinbun.kyoto-u.ac.jp/canvas/M043/M0430002_15"
            }
          ]
        }
      ]
    },
    {
      "id": "https://toho-digital-library.zinbun.kyoto-u.ac.jp/canvas/M043/M0430002_16",
      "type": "Canvas",
      "label": {
        "zh": [
          "表 - 第16頁"
        ],
        "en": [
          "表 - 第16頁"
        ]
      },
      "height": 1400,
      "width": 1000,
      "items": [
        {
          "id": "https://toho-digital-library.zinbun.kyoto-u.ac.jp/canvas/M043/M0430002_16/page/1",
          "type": "AnnotationPage",
          "items": [
            {
              "id": "https://toho-digital-library.zinbun.kyoto-u.ac.jp/canvas/M043/M0430002_16/annotation/1",
              "type": "Annotation",
              "motivation": "painting",
              "body": {
                "id": "https://iiif.toyjack.net/iiif/M043/M0430002_016.jpg",
                "type": "Image",
                "format": "image/jpeg",
                "height": 1400,
                "width": 1000,
                "service": [
                  {
                    "@id": "https://iiif.toyjack.net/iiif/M043%2FM0430016",
                    "@type": "ImageService2",
                    "profile": "http://iiif.io/api/image/2/level2.json"
                  }
                ]
              },
              "target": "https://toho-digital-library.zinbun.kyoto-u.ac.jp/canvas/M043/M0430002_16"
            }
          ]
        }
      ]
    },
    {
      "id": "https://toho-digital-library.zinbun.kyoto-u.ac.jp/canvas/M043/M0430002_17",
      "type": "Canvas",
      "label": {
        "zh": [
          "表 - 第17頁"
        ],
        "en": [
          "表 - 第17頁"
        ]
      },
      "height": 1400,
      "width": 1000,
      "items": [
        {
          "id": "https://toho-digital-library.zinbun.kyoto-u.ac.jp/canvas/M043/M0430002_17/page/1",
          "type": "AnnotationPage",
          "items": [
            {
              "id": "https://toho-digital-library.zinbun.kyoto-u.ac.jp/canvas/M043/M0430002_17/annotation/1",
              "type": "Annotation",
              "motivation": "painting",
              "body": {
                "id": "https://iiif.toyjack.net/iiif/M043/M0430002_017.jpg",
                "type": "Image",
                "format": "image/jpeg",
                "height": 1400,
                "width": 1000,
                "service": [
                  {
                    "@id": "https://iiif.toyjack.net/iiif/M043%2FM0430017",
                    "@type": "ImageService2",
                    "profile": "http://iiif.io/api/image/2/level2.json"
                  }
                ]
              },
              "target": "https://toho-digital-library.zinbun.kyoto-u.ac.jp/canvas/M043/M0430002_17"
            }
          ]
        }
      ]
    },
    {
      "id": "https://toho-digital-library.zinbun.kyoto-u.ac.jp/canvas/M043/M0430002_18",
      "type": "Canvas",
      "label": {
        "zh": [
          "表 - 第18頁"
        ],
        "en": [
          "表 - 第18頁"
        ]
      },
      "height": 1400,
      "width": 1000,
      "items": [
        {
          "id": "https://toho-digital-library.zinbun.kyoto-u.ac.jp/canvas/M043/M0430002_18/page/1",
          "type": "AnnotationPage",
          "items": [
            {
              "id": "https://toho-digital-library.zinbun.kyoto-u.ac.jp/canvas/M043/M0430002_18/annotation/1",
              "type": "Annotation",
              "motivation": "painting",
              "body": {
                "id": "https://iiif.toyjack.net/iiif/M043/M0430002_018.jpg",
                "type": "Image",
                "format": "image/jpeg",
                "height": 1400,
                "width": 1000,
                "service": [
                  {
                    "@id": "https://iiif.toyjack.net/iiif/M043%2FM0430018",
                    "@type": "ImageService2",
                    "profile": "http://iiif.io/api/image/2/level2.json"
                  }
                ]
              },
              "target": "https://toho-digital-library.zinbun.kyoto-u.ac.jp/canvas/M043/M0430002_18"
            }
          ]
        }
      ]
    }
  ]
}