{
  "@context": [
    "http://www.w3.org/ns/anno.jsonld",
    "http://iiif.io/api/presentation/3/context.json"
  ],
  "id": "https://toyjack.github.io/toho-html-data/manifests/C002.json",
  "type": "Manifest",
  "label": {
    "zh": [
      "大明嘉靖二十年歳次辛丑大統曆　一卷"
    ],
    "en": [
      "大明嘉靖二十年歳次辛丑大統曆　一卷"
    ]
  },
  "metadata": [
    {
      "label": {
        "en": [
          "Title"
        ],
        "zh": [
          "書名"
        ]
      },
      "value": {
        "zh": [
          "大明嘉靖二十年歳次辛丑大統曆　一卷"
        ]
      }
    },
    {
      "label": {
        "en": [
          "Category"
        ],
        "zh": [
          "類別"
        ]
      },
      "value": {
        "zh": [
          "子部"
        ]
      }
    },
    {
      "label": {
        "en": [
          "Dynasty"
        ],
        "zh": [
          "朝代"
        ]
      },
      "value": {
        "zh": [
          "明"
        ]
      }
    },
    {
      "label": {
        "en": [
          "Publication Info"
        ],
        "zh": [
          "版本信息"
        ]
      },
      "value": {
        "zh": [
          "明刊本"
        ]
      }
    },
    {
      "label": {
        "en": [
          "Volumes"
        ],
        "zh": [
          "卷數"
        ]
      },
      "value": {
        "zh": [
          "一卷"
        ]
      }
    },
    {
      "label": {
        "en": [
          "Book Type"
        ],
        "zh": [
          "版本類型"
        ]
      },
      "value": {
        "zh": [
          "刊本"
        ]
      }
    }
  ],
  "summary": {
    "zh": [
      "明刊本"
    ],
    "en": [
      "明刊本"
    ]
  },
  "viewingDirection": "right-to-left",
  "requiredStatement": {
    "label": {
      "en": [
        "Attribution"
      ],
      "zh": [
        "歸屬"
      ]
    },
    "value": {
      "zh": [
        "東方學数字圖書館"
      ],
      "ja": [
        "東方學デジタル圖書館"
      ],
      "en": [
        "Oriental Studies Digital Library"
      ]
    }
  },
  "rights": "http://creativecommons.org/licenses/by-nc/4.0/",
  "provider": [
    {
      "id": "https://toyjack.github.io/toho-html-data",
      "type": "Agent",
      "label": {
        "ja": [
          "東方學デジタル圖書館"
        ]
      },
      "homepage": [
        {
          "id": "https://toyjack.github.io/toho-html-data",
          "type": "Text",
          "label": {
            "ja": [
              "東方學デジタル圖書館"
            ]
          },
          "format": "text/html"
        }
      ]
    }
  ],
  "items": [
    {
      "id": "https://toyjack.github.io/toho-html-data/canvas/C002/C0020001_1",
      "type": "Canvas",
      "label": {
        "zh": [
          "　 - 第1頁"
        ],
        "en": [
          "　 - 第1頁"
        ]
      },
      "height": 1400,
      "width": 1000,
      "items": [
        {
          "id": "https://toyjack.github.io/toho-html-data/canvas/C002/C0020001_1/page/1",
          "type": "AnnotationPage",
          "items": [
            {
              "id": "https://toyjack.github.io/toho-html-data/canvas/C002/C0020001_1/annotation/1",
              "type": "Annotation",
              "motivation": "painting",
              "body": {
                "id": "https://image.kanji.zinbun.kyoto-u.ac.jp/toho/iiif/C002/C0020001_001.jpg",
                "type": "Image",
                "format": "image/jpeg",
                "height": 1400,
                "width": 1000,
                "service": [
                  {
                    "id": "https://image.kanji.zinbun.kyoto-u.ac.jp/toho/iiif/C002%2FC0020001",
                    "type": "ImageService3",
                    "profile": "level2"
                  }
                ]
              },
              "target": "https://toyjack.github.io/toho-html-data/canvas/C002/C0020001_1"
            }
          ]
        }
      ]
    },
    {
      "id": "https://toyjack.github.io/toho-html-data/canvas/C002/C0020001_2",
      "type": "Canvas",
      "label": {
        "zh": [
          "　 - 第2頁"
        ],
        "en": [
          "　 - 第2頁"
        ]
      },
      "height": 1400,
      "width": 1000,
      "items": [
        {
          "id": "https://toyjack.github.io/toho-html-data/canvas/C002/C0020001_2/page/1",
          "type": "AnnotationPage",
          "items": [
            {
              "id": "https://toyjack.github.io/toho-html-data/canvas/C002/C0020001_2/annotation/1",
              "type": "Annotation",
              "motivation": "painting",
              "body": {
                "id": "https://image.kanji.zinbun.kyoto-u.ac.jp/toho/iiif/C002/C0020001_002.jpg",
                "type": "Image",
                "format": "image/jpeg",
                "height": 1400,
                "width": 1000,
                "service": [
                  {
                    "id": "https://image.kanji.zinbun.kyoto-u.ac.jp/toho/iiif/C002%2FC0020002",
                    "type": "ImageService3",
                    "profile": "level2"
                  }
                ]
              },
              "target": "https://toyjack.github.io/toho-html-data/canvas/C002/C0020001_2"
            }
          ]
        }
      ]
    },
    {
      "id": "https://toyjack.github.io/toho-html-data/canvas/C002/C0020001_3",
      "type": "Canvas",
      "label": {
        "zh": [
          "　 - 第3頁"
        ],
        "en": [
          "　 - 第3頁"
        ]
      },
      "height": 1400,
      "width": 1000,
      "items": [
        {
          "id": "https://toyjack.github.io/toho-html-data/canvas/C002/C0020001_3/page/1",
          "type": "AnnotationPage",
          "items": [
            {
              "id": "https://toyjack.github.io/toho-html-data/canvas/C002/C0020001_3/annotation/1",
              "type": "Annotation",
              "motivation": "painting",
              "body": {
                "id": "https://image.kanji.zinbun.kyoto-u.ac.jp/toho/iiif/C002/C0020001_003.jpg",
                "type": "Image",
                "format": "image/jpeg",
                "height": 1400,
                "width": 1000,
                "service": [
                  {
                    "id": "https://image.kanji.zinbun.kyoto-u.ac.jp/toho/iiif/C002%2FC0020003",
                    "type": "ImageService3",
                    "profile": "level2"
                  }
                ]
              },
              "target": "https://toyjack.github.io/toho-html-data/canvas/C002/C0020001_3"
            }
          ]
        }
      ]
    },
    {
      "id": "https://toyjack.github.io/toho-html-data/canvas/C002/C0020001_4",
      "type": "Canvas",
      "label": {
        "zh": [
          "　 - 第4頁"
        ],
        "en": [
          "　 - 第4頁"
        ]
      },
      "height": 1400,
      "width": 1000,
      "items": [
        {
          "id": "https://toyjack.github.io/toho-html-data/canvas/C002/C0020001_4/page/1",
          "type": "AnnotationPage",
          "items": [
            {
              "id": "https://toyjack.github.io/toho-html-data/canvas/C002/C0020001_4/annotation/1",
              "type": "Annotation",
              "motivation": "painting",
              "body": {
                "id": "https://image.kanji.zinbun.kyoto-u.ac.jp/toho/iiif/C002/C0020001_004.jpg",
                "type": "Image",
                "format": "image/jpeg",
                "height": 1400,
                "width": 1000,
                "service": [
                  {
                    "id": "https://image.kanji.zinbun.kyoto-u.ac.jp/toho/iiif/C002%2FC0020004",
                    "type": "ImageService3",
                    "profile": "level2"
                  }
                ]
              },
              "target": "https://toyjack.github.io/toho-html-data/canvas/C002/C0020001_4"
            }
          ]
        }
      ]
    },
    {
      "id": "https://toyjack.github.io/toho-html-data/canvas/C002/C0020001_5",
      "type": "Canvas",
      "label": {
        "zh": [
          "　 - 第5頁"
        ],
        "en": [
          "　 - 第5頁"
        ]
      },
      "height": 1400,
      "width": 1000,
      "items": [
        {
          "id": "https://toyjack.github.io/toho-html-data/canvas/C002/C0020001_5/page/1",
          "type": "AnnotationPage",
          "items": [
            {
              "id": "https://toyjack.github.io/toho-html-data/canvas/C002/C0020001_5/annotation/1",
              "type": "Annotation",
              "motivation": "painting",
              "body": {
                "id": "https://image.kanji.zinbun.kyoto-u.ac.jp/toho/iiif/C002/C0020001_005.jpg",
                "type": "Image",
                "format": "image/jpeg",
                "height": 1400,
                "width": 1000,
                "service": [
                  {
                    "id": "https://image.kanji.zinbun.kyoto-u.ac.jp/toho/iiif/C002%2FC0020005",
                    "type": "ImageService3",
                    "profile": "level2"
                  }
                ]
              },
              "target": "https://toyjack.github.io/toho-html-data/canvas/C002/C0020001_5"
            }
          ]
        }
      ]
    },
    {
      "id": "https://toyjack.github.io/toho-html-data/canvas/C002/C0020001_6",
      "type": "Canvas",
      "label": {
        "zh": [
          "　 - 第6頁"
        ],
        "en": [
          "　 - 第6頁"
        ]
      },
      "height": 1400,
      "width": 1000,
      "items": [
        {
          "id": "https://toyjack.github.io/toho-html-data/canvas/C002/C0020001_6/page/1",
          "type": "AnnotationPage",
          "items": [
            {
              "id": "https://toyjack.github.io/toho-html-data/canvas/C002/C0020001_6/annotation/1",
              "type": "Annotation",
              "motivation": "painting",
              "body": {
                "id": "https://image.kanji.zinbun.kyoto-u.ac.jp/toho/iiif/C002/C0020001_006.jpg",
                "type": "Image",
                "format": "image/jpeg",
                "height": 1400,
                "width": 1000,
                "service": [
                  {
                    "id": "https://image.kanji.zinbun.kyoto-u.ac.jp/toho/iiif/C002%2FC0020006",
                    "type": "ImageService3",
                    "profile": "level2"
                  }
                ]
              },
              "target": "https://toyjack.github.io/toho-html-data/canvas/C002/C0020001_6"
            }
          ]
        }
      ]
    },
    {
      "id": "https://toyjack.github.io/toho-html-data/canvas/C002/C0020001_7",
      "type": "Canvas",
      "label": {
        "zh": [
          "　 - 第7頁"
        ],
        "en": [
          "　 - 第7頁"
        ]
      },
      "height": 1400,
      "width": 1000,
      "items": [
        {
          "id": "https://toyjack.github.io/toho-html-data/canvas/C002/C0020001_7/page/1",
          "type": "AnnotationPage",
          "items": [
            {
              "id": "https://toyjack.github.io/toho-html-data/canvas/C002/C0020001_7/annotation/1",
              "type": "Annotation",
              "motivation": "painting",
              "body": {
                "id": "https://image.kanji.zinbun.kyoto-u.ac.jp/toho/iiif/C002/C0020001_007.jpg",
                "type": "Image",
                "format": "image/jpeg",
                "height": 1400,
                "width": 1000,
                "service": [
                  {
                    "id": "https://image.kanji.zinbun.kyoto-u.ac.jp/toho/iiif/C002%2FC0020007",
                    "type": "ImageService3",
                    "profile": "level2"
                  }
                ]
              },
              "target": "https://toyjack.github.io/toho-html-data/canvas/C002/C0020001_7"
            }
          ]
        }
      ]
    },
    {
      "id": "https://toyjack.github.io/toho-html-data/canvas/C002/C0020001_8",
      "type": "Canvas",
      "label": {
        "zh": [
          "　 - 第8頁"
        ],
        "en": [
          "　 - 第8頁"
        ]
      },
      "height": 1400,
      "width": 1000,
      "items": [
        {
          "id": "https://toyjack.github.io/toho-html-data/canvas/C002/C0020001_8/page/1",
          "type": "AnnotationPage",
          "items": [
            {
              "id": "https://toyjack.github.io/toho-html-data/canvas/C002/C0020001_8/annotation/1",
              "type": "Annotation",
              "motivation": "painting",
              "body": {
                "id": "https://image.kanji.zinbun.kyoto-u.ac.jp/toho/iiif/C002/C0020001_008.jpg",
                "type": "Image",
                "format": "image/jpeg",
                "height": 1400,
                "width": 1000,
                "service": [
                  {
                    "id": "https://image.kanji.zinbun.kyoto-u.ac.jp/toho/iiif/C002%2FC0020008",
                    "type": "ImageService3",
                    "profile": "level2"
                  }
                ]
              },
              "target": "https://toyjack.github.io/toho-html-data/canvas/C002/C0020001_8"
            }
          ]
        }
      ]
    },
    {
      "id": "https://toyjack.github.io/toho-html-data/canvas/C002/C0020001_9",
      "type": "Canvas",
      "label": {
        "zh": [
          "　 - 第9頁"
        ],
        "en": [
          "　 - 第9頁"
        ]
      },
      "height": 1400,
      "width": 1000,
      "items": [
        {
          "id": "https://toyjack.github.io/toho-html-data/canvas/C002/C0020001_9/page/1",
          "type": "AnnotationPage",
          "items": [
            {
              "id": "https://toyjack.github.io/toho-html-data/canvas/C002/C0020001_9/annotation/1",
              "type": "Annotation",
              "motivation": "painting",
              "body": {
                "id": "https://image.kanji.zinbun.kyoto-u.ac.jp/toho/iiif/C002/C0020001_009.jpg",
                "type": "Image",
                "format": "image/jpeg",
                "height": 1400,
                "width": 1000,
                "service": [
                  {
                    "id": "https://image.kanji.zinbun.kyoto-u.ac.jp/toho/iiif/C002%2FC0020009",
                    "type": "ImageService3",
                    "profile": "level2"
                  }
                ]
              },
              "target": "https://toyjack.github.io/toho-html-data/canvas/C002/C0020001_9"
            }
          ]
        }
      ]
    },
    {
      "id": "https://toyjack.github.io/toho-html-data/canvas/C002/C0020001_10",
      "type": "Canvas",
      "label": {
        "zh": [
          "　 - 第10頁"
        ],
        "en": [
          "　 - 第10頁"
        ]
      },
      "height": 1400,
      "width": 1000,
      "items": [
        {
          "id": "https://toyjack.github.io/toho-html-data/canvas/C002/C0020001_10/page/1",
          "type": "AnnotationPage",
          "items": [
            {
              "id": "https://toyjack.github.io/toho-html-data/canvas/C002/C0020001_10/annotation/1",
              "type": "Annotation",
              "motivation": "painting",
              "body": {
                "id": "https://image.kanji.zinbun.kyoto-u.ac.jp/toho/iiif/C002/C0020001_010.jpg",
                "type": "Image",
                "format": "image/jpeg",
                "height": 1400,
                "width": 1000,
                "service": [
                  {
                    "id": "https://image.kanji.zinbun.kyoto-u.ac.jp/toho/iiif/C002%2FC0020010",
                    "type": "ImageService3",
                    "profile": "level2"
                  }
                ]
              },
              "target": "https://toyjack.github.io/toho-html-data/canvas/C002/C0020001_10"
            }
          ]
        }
      ]
    },
    {
      "id": "https://toyjack.github.io/toho-html-data/canvas/C002/C0020001_11",
      "type": "Canvas",
      "label": {
        "zh": [
          "　 - 第11頁"
        ],
        "en": [
          "　 - 第11頁"
        ]
      },
      "height": 1400,
      "width": 1000,
      "items": [
        {
          "id": "https://toyjack.github.io/toho-html-data/canvas/C002/C0020001_11/page/1",
          "type": "AnnotationPage",
          "items": [
            {
              "id": "https://toyjack.github.io/toho-html-data/canvas/C002/C0020001_11/annotation/1",
              "type": "Annotation",
              "motivation": "painting",
              "body": {
                "id": "https://image.kanji.zinbun.kyoto-u.ac.jp/toho/iiif/C002/C0020001_011.jpg",
                "type": "Image",
                "format": "image/jpeg",
                "height": 1400,
                "width": 1000,
                "service": [
                  {
                    "id": "https://image.kanji.zinbun.kyoto-u.ac.jp/toho/iiif/C002%2FC0020011",
                    "type": "ImageService3",
                    "profile": "level2"
                  }
                ]
              },
              "target": "https://toyjack.github.io/toho-html-data/canvas/C002/C0020001_11"
            }
          ]
        }
      ]
    },
    {
      "id": "https://toyjack.github.io/toho-html-data/canvas/C002/C0020001_12",
      "type": "Canvas",
      "label": {
        "zh": [
          "　 - 第12頁"
        ],
        "en": [
          "　 - 第12頁"
        ]
      },
      "height": 1400,
      "width": 1000,
      "items": [
        {
          "id": "https://toyjack.github.io/toho-html-data/canvas/C002/C0020001_12/page/1",
          "type": "AnnotationPage",
          "items": [
            {
              "id": "https://toyjack.github.io/toho-html-data/canvas/C002/C0020001_12/annotation/1",
              "type": "Annotation",
              "motivation": "painting",
              "body": {
                "id": "https://image.kanji.zinbun.kyoto-u.ac.jp/toho/iiif/C002/C0020001_012.jpg",
                "type": "Image",
                "format": "image/jpeg",
                "height": 1400,
                "width": 1000,
                "service": [
                  {
                    "id": "https://image.kanji.zinbun.kyoto-u.ac.jp/toho/iiif/C002%2FC0020012",
                    "type": "ImageService3",
                    "profile": "level2"
                  }
                ]
              },
              "target": "https://toyjack.github.io/toho-html-data/canvas/C002/C0020001_12"
            }
          ]
        }
      ]
    },
    {
      "id": "https://toyjack.github.io/toho-html-data/canvas/C002/C0020001_13",
      "type": "Canvas",
      "label": {
        "zh": [
          "　 - 第13頁"
        ],
        "en": [
          "　 - 第13頁"
        ]
      },
      "height": 1400,
      "width": 1000,
      "items": [
        {
          "id": "https://toyjack.github.io/toho-html-data/canvas/C002/C0020001_13/page/1",
          "type": "AnnotationPage",
          "items": [
            {
              "id": "https://toyjack.github.io/toho-html-data/canvas/C002/C0020001_13/annotation/1",
              "type": "Annotation",
              "motivation": "painting",
              "body": {
                "id": "https://image.kanji.zinbun.kyoto-u.ac.jp/toho/iiif/C002/C0020001_013.jpg",
                "type": "Image",
                "format": "image/jpeg",
                "height": 1400,
                "width": 1000,
                "service": [
                  {
                    "id": "https://image.kanji.zinbun.kyoto-u.ac.jp/toho/iiif/C002%2FC0020013",
                    "type": "ImageService3",
                    "profile": "level2"
                  }
                ]
              },
              "target": "https://toyjack.github.io/toho-html-data/canvas/C002/C0020001_13"
            }
          ]
        }
      ]
    },
    {
      "id": "https://toyjack.github.io/toho-html-data/canvas/C002/C0020001_14",
      "type": "Canvas",
      "label": {
        "zh": [
          "　 - 第14頁"
        ],
        "en": [
          "　 - 第14頁"
        ]
      },
      "height": 1400,
      "width": 1000,
      "items": [
        {
          "id": "https://toyjack.github.io/toho-html-data/canvas/C002/C0020001_14/page/1",
          "type": "AnnotationPage",
          "items": [
            {
              "id": "https://toyjack.github.io/toho-html-data/canvas/C002/C0020001_14/annotation/1",
              "type": "Annotation",
              "motivation": "painting",
              "body": {
                "id": "https://image.kanji.zinbun.kyoto-u.ac.jp/toho/iiif/C002/C0020001_014.jpg",
                "type": "Image",
                "format": "image/jpeg",
                "height": 1400,
                "width": 1000,
                "service": [
                  {
                    "id": "https://image.kanji.zinbun.kyoto-u.ac.jp/toho/iiif/C002%2FC0020014",
                    "type": "ImageService3",
                    "profile": "level2"
                  }
                ]
              },
              "target": "https://toyjack.github.io/toho-html-data/canvas/C002/C0020001_14"
            }
          ]
        }
      ]
    },
    {
      "id": "https://toyjack.github.io/toho-html-data/canvas/C002/C0020001_15",
      "type": "Canvas",
      "label": {
        "zh": [
          "　 - 第15頁"
        ],
        "en": [
          "　 - 第15頁"
        ]
      },
      "height": 1400,
      "width": 1000,
      "items": [
        {
          "id": "https://toyjack.github.io/toho-html-data/canvas/C002/C0020001_15/page/1",
          "type": "AnnotationPage",
          "items": [
            {
              "id": "https://toyjack.github.io/toho-html-data/canvas/C002/C0020001_15/annotation/1",
              "type": "Annotation",
              "motivation": "painting",
              "body": {
                "id": "https://image.kanji.zinbun.kyoto-u.ac.jp/toho/iiif/C002/C0020001_015.jpg",
                "type": "Image",
                "format": "image/jpeg",
                "height": 1400,
                "width": 1000,
                "service": [
                  {
                    "id": "https://image.kanji.zinbun.kyoto-u.ac.jp/toho/iiif/C002%2FC0020015",
                    "type": "ImageService3",
                    "profile": "level2"
                  }
                ]
              },
              "target": "https://toyjack.github.io/toho-html-data/canvas/C002/C0020001_15"
            }
          ]
        }
      ]
    },
    {
      "id": "https://toyjack.github.io/toho-html-data/canvas/C002/C0020001_16",
      "type": "Canvas",
      "label": {
        "zh": [
          "　 - 第16頁"
        ],
        "en": [
          "　 - 第16頁"
        ]
      },
      "height": 1400,
      "width": 1000,
      "items": [
        {
          "id": "https://toyjack.github.io/toho-html-data/canvas/C002/C0020001_16/page/1",
          "type": "AnnotationPage",
          "items": [
            {
              "id": "https://toyjack.github.io/toho-html-data/canvas/C002/C0020001_16/annotation/1",
              "type": "Annotation",
              "motivation": "painting",
              "body": {
                "id": "https://image.kanji.zinbun.kyoto-u.ac.jp/toho/iiif/C002/C0020001_016.jpg",
                "type": "Image",
                "format": "image/jpeg",
                "height": 1400,
                "width": 1000,
                "service": [
                  {
                    "id": "https://image.kanji.zinbun.kyoto-u.ac.jp/toho/iiif/C002%2FC0020016",
                    "type": "ImageService3",
                    "profile": "level2"
                  }
                ]
              },
              "target": "https://toyjack.github.io/toho-html-data/canvas/C002/C0020001_16"
            }
          ]
        }
      ]
    },
    {
      "id": "https://toyjack.github.io/toho-html-data/canvas/C002/C0020001_17",
      "type": "Canvas",
      "label": {
        "zh": [
          "　 - 第17頁"
        ],
        "en": [
          "　 - 第17頁"
        ]
      },
      "height": 1400,
      "width": 1000,
      "items": [
        {
          "id": "https://toyjack.github.io/toho-html-data/canvas/C002/C0020001_17/page/1",
          "type": "AnnotationPage",
          "items": [
            {
              "id": "https://toyjack.github.io/toho-html-data/canvas/C002/C0020001_17/annotation/1",
              "type": "Annotation",
              "motivation": "painting",
              "body": {
                "id": "https://image.kanji.zinbun.kyoto-u.ac.jp/toho/iiif/C002/C0020001_017.jpg",
                "type": "Image",
                "format": "image/jpeg",
                "height": 1400,
                "width": 1000,
                "service": [
                  {
                    "id": "https://image.kanji.zinbun.kyoto-u.ac.jp/toho/iiif/C002%2FC0020017",
                    "type": "ImageService3",
                    "profile": "level2"
                  }
                ]
              },
              "target": "https://toyjack.github.io/toho-html-data/canvas/C002/C0020001_17"
            }
          ]
        }
      ]
    },
    {
      "id": "https://toyjack.github.io/toho-html-data/canvas/C002/C0020001_18",
      "type": "Canvas",
      "label": {
        "zh": [
          "　 - 第18頁"
        ],
        "en": [
          "　 - 第18頁"
        ]
      },
      "height": 1400,
      "width": 1000,
      "items": [
        {
          "id": "https://toyjack.github.io/toho-html-data/canvas/C002/C0020001_18/page/1",
          "type": "AnnotationPage",
          "items": [
            {
              "id": "https://toyjack.github.io/toho-html-data/canvas/C002/C0020001_18/annotation/1",
              "type": "Annotation",
              "motivation": "painting",
              "body": {
                "id": "https://image.kanji.zinbun.kyoto-u.ac.jp/toho/iiif/C002/C0020001_018.jpg",
                "type": "Image",
                "format": "image/jpeg",
                "height": 1400,
                "width": 1000,
                "service": [
                  {
                    "id": "https://image.kanji.zinbun.kyoto-u.ac.jp/toho/iiif/C002%2FC0020018",
                    "type": "ImageService3",
                    "profile": "level2"
                  }
                ]
              },
              "target": "https://toyjack.github.io/toho-html-data/canvas/C002/C0020001_18"
            }
          ]
        }
      ]
    },
    {
      "id": "https://toyjack.github.io/toho-html-data/canvas/C002/C0020001_19",
      "type": "Canvas",
      "label": {
        "zh": [
          "　 - 第19頁"
        ],
        "en": [
          "　 - 第19頁"
        ]
      },
      "height": 1400,
      "width": 1000,
      "items": [
        {
          "id": "https://toyjack.github.io/toho-html-data/canvas/C002/C0020001_19/page/1",
          "type": "AnnotationPage",
          "items": [
            {
              "id": "https://toyjack.github.io/toho-html-data/canvas/C002/C0020001_19/annotation/1",
              "type": "Annotation",
              "motivation": "painting",
              "body": {
                "id": "https://image.kanji.zinbun.kyoto-u.ac.jp/toho/iiif/C002/C0020001_019.jpg",
                "type": "Image",
                "format": "image/jpeg",
                "height": 1400,
                "width": 1000,
                "service": [
                  {
                    "id": "https://image.kanji.zinbun.kyoto-u.ac.jp/toho/iiif/C002%2FC0020019",
                    "type": "ImageService3",
                    "profile": "level2"
                  }
                ]
              },
              "target": "https://toyjack.github.io/toho-html-data/canvas/C002/C0020001_19"
            }
          ]
        }
      ]
    },
    {
      "id": "https://toyjack.github.io/toho-html-data/canvas/C002/C0020001_20",
      "type": "Canvas",
      "label": {
        "zh": [
          "　 - 第20頁"
        ],
        "en": [
          "　 - 第20頁"
        ]
      },
      "height": 1400,
      "width": 1000,
      "items": [
        {
          "id": "https://toyjack.github.io/toho-html-data/canvas/C002/C0020001_20/page/1",
          "type": "AnnotationPage",
          "items": [
            {
              "id": "https://toyjack.github.io/toho-html-data/canvas/C002/C0020001_20/annotation/1",
              "type": "Annotation",
              "motivation": "painting",
              "body": {
                "id": "https://image.kanji.zinbun.kyoto-u.ac.jp/toho/iiif/C002/C0020001_020.jpg",
                "type": "Image",
                "format": "image/jpeg",
                "height": 1400,
                "width": 1000,
                "service": [
                  {
                    "id": "https://image.kanji.zinbun.kyoto-u.ac.jp/toho/iiif/C002%2FC0020020",
                    "type": "ImageService3",
                    "profile": "level2"
                  }
                ]
              },
              "target": "https://toyjack.github.io/toho-html-data/canvas/C002/C0020001_20"
            }
          ]
        }
      ]
    }
  ]
}